fastgps-1.1.dist-info/METADATA
fastgps-1.1.dist-info/WHEEL
fastgps-1.1.dist-info/entry_points.txt
fastgps-1.1.dist-info/licenses/LICENSE
fastgps/__init__.py
fastgps/abstract_fast_gp.py
fastgps/abstract_gp.py
fastgps/fast_gp_digital_net_b2.py
fastgps/fast_gp_lattice.py
fastgps/plots.py
fastgps/standard_gp.py
fastgps/util.py
fastgps-1.1.dist-info/RECORD
